eeval/__init__.py
eeval/__main__.py
eeval/client/__init__.py
eeval/client/client.py
eeval/client/exceptions.py
eeval/server/__init__.py
eeval/server/main.py
eeval/server/models/__init__.py
eeval/server/models/abstract_model.py
eeval/server/models/exceptions.py
eeval/server/models/linear_layer.py
eeval-0.1.2.dist-info/LICENSE
eeval-0.1.2.dist-info/METADATA
eeval-0.1.2.dist-info/WHEEL
eeval-0.1.2.dist-info/entry_points.txt
eeval-0.1.2.dist-info/top_level.txt
eeval-0.1.2.dist-info/RECORD
