Metadata-Version: 2.1
Name: eeval
Version: 0.1.2
Summary: Client/Server framework for encrypted machine learning evaluation
Home-page: https://github.com/youben11/encrypted-evaluation
Author: Ayoub Benaissa
Author-email: ayouben9@gmail.com
License: GPL3
Keywords: homomorphic encryption machine learning
Platform: UNKNOWN
Classifier: Programming Language :: Python :: 3
Classifier: Operating System :: OS Independent
Requires-Dist: fastapi (~=0.60.0)
Requires-Dist: numpy (~=1.18.0)
Requires-Dist: tenseal (~=0.1.0)
Requires-Dist: typer[all] (~=0.3.0)
Requires-Dist: uvicorn (~=0.11.0)
